<annotation version="1.3">
  <image>sv_nvdx_ar0138_20210513_172537.h265_ch00_003600.jpg</image>
  <size>
    <width>1280</width>
    <height>960</height>
  </size>
  <labeled name="od">1.3</labeled>
  <object>
    <name>pedestrian</name>
    <subname>pedestrian</subname>
    <object_id>1</object_id>
    <bndbox left="375.92" top="248.82" right="448.14" bottom="524.48" />
    <fitbox>
      <point x="375.92" y="248.82" />
      <point x="448.14" y="248.82" />
      <point x="448.14" y="524.48" />
      <point x="375.92" y="524.48" />
    </fitbox>
  </object>
  <object>
    <name>pedestrian</name>
    <subname>pedestrian</subname>
    <object_id>1</object_id>
    <bndbox left="577.42" top="379.67" right="600.18" bottom="448.98" />
    <fitbox>
      <point x="577.42" y="379.67" />
      <point x="600.18" y="379.67" />
      <point x="600.18" y="448.98" />
      <point x="577.42" y="448.98" />
    </fitbox>
  </object>
  <object>
    <name>pedestrian</name>
    <subname>pedestrian</subname>
    <object_id>1</object_id>
    <bndbox left="297.85" top="301.83" right="354.11" bottom="504.26" />
    <fitbox>
      <point x="297.85" y="301.83" />
      <point x="354.11" y="301.83" />
      <point x="354.11" y="504.26" />
      <point x="297.85" y="504.26" />
    </fitbox>
  </object>
  <object>
    <name>pedestrian</name>
    <subname>pedestrian</subname>
    <object_id>1</object_id>
    <bndbox left="784.05" top="376.18" right="810.60" bottom="455.27" />
    <fitbox>
      <point x="784.05" y="376.18" />
      <point x="810.60" y="376.18" />
      <point x="810.60" y="455.27" />
      <point x="784.05" y="455.27" />
    </fitbox>
  </object>
  <object>
    <name>pedestrian</name>
    <subname>pedestrian</subname>
    <object_id>1</object_id>
    <bndbox left="856.70" top="256.75" right="941.71" bottom="529.05" />
    <fitbox>
      <point x="856.70" y="256.75" />
      <point x="941.71" y="256.75" />
      <point x="941.71" y="529.05" />
      <point x="856.70" y="529.05" />
    </fitbox>
  </object>
  <object>
    <name>pedestrian</name>
    <subname>pedestrian</subname>
    <object_id>1</object_id>
    <bndbox left="1165.65" top="465.41" right="1183.49" bottom="522.55" />
    <fitbox>
      <point x="1165.65" y="465.41" />
      <point x="1183.49" y="465.41" />
      <point x="1183.49" y="522.55" />
      <point x="1165.65" y="522.55" />
    </fitbox>
  </object>
  <object>
    <name>pedestrian</name>
    <subname>pedestrian</subname>
    <object_id>1</object_id>
    <bndbox left="331.27" top="300.68" right="390.26" bottom="512.46" />
    <fitbox>
      <point x="331.27" y="300.68" />
      <point x="390.26" y="300.68" />
      <point x="390.26" y="512.46" />
      <point x="331.27" y="512.46" />
    </fitbox>
  </object>
  <object>
    <name>pedestrian</name>
    <subname>pedestrian</subname>
    <object_id>1</object_id>
    <bndbox left="1222.19" top="461.55" right="1243.48" bottom="539.29" />
    <fitbox>
      <point x="1222.19" y="461.55" />
      <point x="1243.48" y="461.55" />
      <point x="1243.48" y="539.29" />
      <point x="1222.19" y="539.29" />
    </fitbox>
  </object>
  <object>
    <name>pedestrian</name>
    <subname>pedestrian</subname>
    <object_id>1</object_id>
    <bndbox left="543.92" top="382.52" right="566.36" bottom="454.56" />
    <fitbox>
      <point x="543.92" y="382.52" />
      <point x="566.36" y="382.52" />
      <point x="566.36" y="454.56" />
      <point x="543.92" y="454.56" />
    </fitbox>
  </object>
  <object>
    <name>pedestrian</name>
    <subname>pedestrian</subname>
    <object_id>1</object_id>
    <bndbox left="556.78" top="382.18" right="578.59" bottom="449.68" />
    <fitbox>
      <point x="556.78" y="382.18" />
      <point x="578.59" y="382.18" />
      <point x="578.59" y="449.68" />
      <point x="556.78" y="449.68" />
    </fitbox>
  </object>
  <object>
    <name>pedestrian</name>
    <subname>pedestrian</subname>
    <object_id>1</object_id>
    <bndbox left="906.08" top="278.18" right="982.64" bottom="527.75" />
    <fitbox>
      <point x="906.08" y="278.18" />
      <point x="982.64" y="278.18" />
      <point x="982.64" y="527.75" />
      <point x="906.08" y="527.75" />
    </fitbox>
  </object>
  <object>
    <name>pedestrian</name>
    <subname>pedestrian</subname>
    <object_id>1</object_id>
    <bndbox left="1207.01" top="459.37" right="1226.20" bottom="537.31" />
    <fitbox>
      <point x="1207.01" y="459.37" />
      <point x="1226.20" y="459.37" />
      <point x="1226.20" y="537.31" />
      <point x="1207.01" y="537.31" />
    </fitbox>
  </object>
  <object>
    <name>ignored</name>
    <subname>ignored_pedestrian</subname>
    <object_id>11</object_id>
    <bndbox left="798.09" top="378.30" right="811.20" bottom="454.77" />
    <fitbox>
      <point x="798.09" y="378.30" />
      <point x="811.20" y="378.30" />
      <point x="811.20" y="454.77" />
      <point x="798.09" y="454.77" />
    </fitbox>
  </object>
  <object>
    <name>pedestrian</name>
    <subname>pedestrian</subname>
    <object_id>12</object_id>
    <bndbox left="606.33" top="398.56" right="617.82" bottom="433.59" />
    <fitbox>
      <point x="606.33" y="398.56" />
      <point x="617.82" y="398.56" />
      <point x="617.82" y="433.59" />
      <point x="606.33" y="433.59" />
    </fitbox>
  </object>
  <object>
    <name>pedestrian</name>
    <subname>pedestrian</subname>
    <object_id>13</object_id>
    <bndbox left="628.36" top="401.38" right="637.78" bottom="432.27" />
    <fitbox>
      <point x="628.36" y="401.38" />
      <point x="637.78" y="401.38" />
      <point x="637.78" y="432.27" />
      <point x="628.36" y="432.27" />
    </fitbox>
  </object>
  <object>
    <name>pedestrian</name>
    <subname>pedestrian</subname>
    <object_id>14</object_id>
    <bndbox left="637.59" top="397.99" right="648.71" bottom="432.27" />
    <fitbox>
      <point x="637.59" y="397.99" />
      <point x="648.71" y="397.99" />
      <point x="648.71" y="432.27" />
      <point x="637.59" y="432.27" />
    </fitbox>
  </object>
  <object>
    <name>pedestrian</name>
    <subname>pedestrian</subname>
    <object_id>15</object_id>
    <bndbox left="652.85" top="405.71" right="662.83" bottom="428.69" />
    <fitbox>
      <point x="652.85" y="405.71" />
      <point x="662.83" y="405.71" />
      <point x="662.83" y="428.69" />
      <point x="652.85" y="428.69" />
    </fitbox>
  </object>
  <object>
    <name>truck</name>
    <subname>small_truck</subname>
    <object_id>16</object_id>
    <bndbox left="667.54" top="401.95" right="692.97" bottom="427.75" />
    <fitbox>
      <point x="667.54" y="401.95" />
      <point x="692.97" y="401.95" />
      <point x="692.97" y="427.75" />
      <point x="667.54" y="427.75" />
    </fitbox>
  </object>
  <object>
    <name>pedestrian</name>
    <subname>pedestrian</subname>
    <object_id>17</object_id>
    <bndbox left="1018.68" top="468.92" right="1025.48" bottom="495.02" />
    <fitbox>
      <point x="1018.68" y="468.92" />
      <point x="1025.48" y="468.92" />
      <point x="1025.48" y="495.02" />
      <point x="1018.68" y="495.02" />
    </fitbox>
  </object>
  <object>
    <name>pedestrian</name>
    <subname>pedestrian</subname>
    <object_id>18</object_id>
    <bndbox left="1034.12" top="469.48" right="1044.60" bottom="496.31" />
    <fitbox>
      <point x="1034.12" y="469.48" />
      <point x="1044.60" y="469.48" />
      <point x="1044.60" y="496.31" />
      <point x="1034.12" y="496.31" />
    </fitbox>
  </object>
</annotation>