<annotation version="1.3">
  <image>sv_nvdx_ar0138_20210514_143030.h265_ch00_009720.jpg</image>
  <size>
    <width>1280</width>
    <height>960</height>
  </size>
  <labeled name="od">1.3</labeled>
  <object>
    <name>pedestrian</name>
    <subname>pedestrian</subname>
    <object_id>1</object_id>
    <bndbox left="138.21" top="358.58" right="182.35" bottom="494.55" />
    <fitbox>
      <point x="138.21" y="358.58" />
      <point x="182.35" y="358.58" />
      <point x="182.35" y="494.55" />
      <point x="138.21" y="494.55" />
    </fitbox>
  </object>
  <object>
    <name>pedestrian</name>
    <subname>pedestrian</subname>
    <object_id>1</object_id>
    <bndbox left="1056.03" top="411.84" right="1081.52" bottom="495.03" />
    <fitbox>
      <point x="1056.03" y="411.84" />
      <point x="1081.52" y="411.84" />
      <point x="1081.52" y="495.03" />
      <point x="1056.03" y="495.03" />
    </fitbox>
  </object>
  <object>
    <name>pedestrian</name>
    <subname>pedestrian</subname>
    <object_id>1</object_id>
    <bndbox left="1103.08" top="357.64" right="1149.86" bottom="543.00" />
    <fitbox>
      <point x="1103.08" y="357.64" />
      <point x="1149.86" y="357.64" />
      <point x="1149.86" y="543.00" />
      <point x="1103.08" y="543.00" />
    </fitbox>
  </object>
  <object>
    <name>pedestrian</name>
    <subname>pedestrian</subname>
    <object_id>10</object_id>
    <bndbox left="413.28" top="380.08" right="428.68" bottom="445.70" />
    <fitbox>
      <point x="413.28" y="380.08" />
      <point x="428.68" y="380.08" />
      <point x="428.68" y="445.70" />
      <point x="413.28" y="445.70" />
    </fitbox>
  </object>
  <object>
    <name>pedestrian</name>
    <subname>pedestrian</subname>
    <object_id>1</object_id>
    <bndbox left="1230.60" top="431.62" right="1259.49" bottom="534.07" />
    <fitbox>
      <point x="1230.60" y="431.62" />
      <point x="1259.49" y="431.62" />
      <point x="1259.49" y="534.07" />
      <point x="1230.60" y="534.07" />
    </fitbox>
  </object>
  <object>
    <name>pedestrian</name>
    <subname>pedestrian</subname>
    <object_id>1</object_id>
    <bndbox left="207.63" top="388.41" right="229.02" bottom="477.80" />
    <fitbox>
      <point x="207.63" y="388.41" />
      <point x="229.02" y="388.41" />
      <point x="229.02" y="477.80" />
      <point x="207.63" y="477.80" />
    </fitbox>
  </object>
  <object>
    <name>pedestrian</name>
    <subname>pedestrian</subname>
    <object_id>1</object_id>
    <bndbox left="72.71" top="377.00" right="100.44" bottom="504.37" />
    <fitbox>
      <point x="72.71" y="377.00" />
      <point x="100.44" y="377.00" />
      <point x="100.44" y="504.37" />
      <point x="72.71" y="504.37" />
    </fitbox>
  </object>
  <object>
    <name>pedestrian</name>
    <subname>pedestrian</subname>
    <object_id>10</object_id>
    <bndbox left="1028.74" top="413.02" right="1052.66" bottom="482.82" />
    <fitbox>
      <point x="1028.74" y="413.02" />
      <point x="1052.66" y="413.02" />
      <point x="1052.66" y="482.82" />
      <point x="1028.74" y="482.82" />
    </fitbox>
  </object>
  <object>
    <name>pedestrian</name>
    <subname>pedestrian</subname>
    <object_id>1</object_id>
    <bndbox left="876.87" top="399.11" right="892.34" bottom="456.66" />
    <fitbox>
      <point x="876.87" y="399.11" />
      <point x="892.34" y="399.11" />
      <point x="892.34" y="456.66" />
      <point x="876.87" y="456.66" />
    </fitbox>
  </object>
  <object>
    <name>pedestrian</name>
    <subname>pedestrian</subname>
    <object_id>1</object_id>
    <bndbox left="1146.07" top="406.04" right="1177.58" bottom="519.37" />
    <fitbox>
      <point x="1146.07" y="406.04" />
      <point x="1177.58" y="406.04" />
      <point x="1177.58" y="519.37" />
      <point x="1146.07" y="519.37" />
    </fitbox>
  </object>
  <object>
    <name>rider</name>
    <subname>motorcycle_without_human</subname>
    <object_id>12</object_id>
    <bndbox left="817.46" top="416.63" right="861.03" bottom="448.95" />
    <fitbox>
      <point x="817.46" y="416.63" />
      <point x="861.03" y="416.63" />
      <point x="861.03" y="448.95" />
      <point x="817.46" y="448.95" />
    </fitbox>
  </object>
  <object>
    <name>pedestrian</name>
    <subname>pedestrian</subname>
    <object_id>10</object_id>
    <bndbox left="1190.68" top="454.10" right="1205.78" bottom="501.70" />
    <fitbox>
      <point x="1190.68" y="454.10" />
      <point x="1205.78" y="454.10" />
      <point x="1205.78" y="501.70" />
      <point x="1190.68" y="501.70" />
    </fitbox>
  </object>
  <object>
    <name>pedestrian</name>
    <subname>pedestrian</subname>
    <object_id>10</object_id>
    <bndbox left="192.96" top="395.14" right="216.31" bottom="468.29" />
    <fitbox>
      <point x="192.96" y="395.14" />
      <point x="216.31" y="395.14" />
      <point x="216.31" y="468.29" />
      <point x="192.96" y="468.29" />
    </fitbox>
  </object>
  <object>
    <name>pedestrian</name>
    <subname>pedestrian</subname>
    <object_id>10</object_id>
    <bndbox left="1166.81" top="421.47" right="1189.21" bottom="512.65" />
    <fitbox>
      <point x="1166.81" y="421.47" />
      <point x="1189.21" y="421.47" />
      <point x="1189.21" y="512.65" />
      <point x="1166.81" y="512.65" />
    </fitbox>
  </object>
  <object>
    <name>pedestrian</name>
    <subname>pedestrian</subname>
    <object_id>10</object_id>
    <bndbox left="603.13" top="393.35" right="612.37" bottom="433.69" />
    <fitbox>
      <point x="603.13" y="393.35" />
      <point x="612.37" y="393.35" />
      <point x="612.37" y="433.69" />
      <point x="603.13" y="433.69" />
    </fitbox>
  </object>
  <object>
    <name>pedestrian</name>
    <subname>pedestrian</subname>
    <object_id>10</object_id>
    <bndbox left="1210.78" top="459.28" right="1222.86" bottom="504.99" />
    <fitbox>
      <point x="1210.78" y="459.28" />
      <point x="1222.86" y="459.28" />
      <point x="1222.86" y="504.99" />
      <point x="1210.78" y="504.99" />
    </fitbox>
  </object>
  <object>
    <name>ignored</name>
    <subname>ignored_pedestrian</subname>
    <object_id>13</object_id>
    <bndbox left="131.09" top="400.51" right="148.18" bottom="470.13" />
    <fitbox>
      <point x="131.09" y="400.51" />
      <point x="148.18" y="400.51" />
      <point x="148.18" y="470.13" />
      <point x="131.09" y="470.13" />
    </fitbox>
  </object>
  <object>
    <name>pedestrian</name>
    <subname>pedestrian</subname>
    <object_id>14</object_id>
    <bndbox left="363.42" top="400.77" right="377.90" bottom="435.48" />
    <fitbox>
      <point x="363.42" y="400.77" />
      <point x="377.90" y="400.77" />
      <point x="377.90" y="435.48" />
      <point x="363.42" y="435.48" />
    </fitbox>
  </object>
  <object>
    <name>ignored</name>
    <subname>ignored_pedestrian</subname>
    <object_id>15</object_id>
    <bndbox left="858.32" top="408.54" right="877.74" bottom="454.05" />
    <fitbox>
      <point x="858.32" y="408.54" />
      <point x="877.74" y="408.54" />
      <point x="877.74" y="454.05" />
      <point x="858.32" y="454.05" />
    </fitbox>
  </object>
  <object>
    <name>pedestrian</name>
    <subname>pedestrian</subname>
    <object_id>16</object_id>
    <bndbox left="1225.57" top="467.47" right="1236.92" bottom="507.49" />
    <fitbox>
      <point x="1225.57" y="467.47" />
      <point x="1236.92" y="467.47" />
      <point x="1236.92" y="507.49" />
      <point x="1225.57" y="507.49" />
    </fitbox>
  </object>
  <object>
    <name>pedestrian</name>
    <subname>sitting_person</subname>
    <object_id>17</object_id>
    <bndbox left="675.35" top="407.24" right="686.55" bottom="429.46" />
    <fitbox>
      <point x="675.35" y="407.24" />
      <point x="686.55" y="407.24" />
      <point x="686.55" y="429.46" />
      <point x="675.35" y="429.46" />
    </fitbox>
  </object>
</annotation>