<annotation version="1.3">
  <image>sv_nvdx_ar0138_20210514_121737.h265_ch00_002820.jpg</image>
  <size>
    <width>1280</width>
    <height>960</height>
  </size>
  <labeled name="od">1.3</labeled>
  <object>
    <name>pedestrian</name>
    <subname>pedestrian</subname>
    <object_id>1</object_id>
    <bndbox left="974.14" top="293.26" right="1055.12" bottom="518.64" />
    <fitbox>
      <point x="974.14" y="293.26" />
      <point x="1055.12" y="293.26" />
      <point x="1055.12" y="518.64" />
      <point x="974.14" y="518.64" />
    </fitbox>
  </object>
  <object>
    <name>pedestrian</name>
    <subname>pedestrian</subname>
    <object_id>1</object_id>
    <bndbox left="1154.54" top="300.76" right="1217.37" bottom="569.31" />
    <fitbox>
      <point x="1154.54" y="300.76" />
      <point x="1217.37" y="300.76" />
      <point x="1217.37" y="569.31" />
      <point x="1154.54" y="569.31" />
    </fitbox>
  </object>
  <object>
    <name>pedestrian</name>
    <subname>pedestrian</subname>
    <object_id>1</object_id>
    <bndbox left="899.70" top="360.03" right="932.80" bottom="462.32" />
    <fitbox>
      <point x="899.70" y="360.03" />
      <point x="932.80" y="360.03" />
      <point x="932.80" y="462.32" />
      <point x="899.70" y="462.32" />
    </fitbox>
  </object>
  <object>
    <name>pedestrian</name>
    <subname>pedestrian</subname>
    <object_id>1</object_id>
    <bndbox left="735.94" top="324.38" right="782.92" bottom="466.54" />
    <fitbox>
      <point x="735.94" y="324.38" />
      <point x="782.92" y="324.38" />
      <point x="782.92" y="466.54" />
      <point x="735.94" y="466.54" />
    </fitbox>
  </object>
  <object>
    <name>pedestrian</name>
    <subname>pedestrian</subname>
    <object_id>1</object_id>
    <bndbox left="788.27" top="334.39" right="841.86" bottom="466.94" />
    <fitbox>
      <point x="788.27" y="334.39" />
      <point x="841.86" y="334.39" />
      <point x="841.86" y="466.94" />
      <point x="788.27" y="466.94" />
    </fitbox>
  </object>
  <object>
    <name>car</name>
    <subname>sedan</subname>
    <object_id>4</object_id>
    <bndbox left="585.24" top="388.67" right="632.35" bottom="427.72" />
    <fitbox>
      <point x="585.24" y="388.67" />
      <point x="632.35" y="388.67" />
      <point x="632.35" y="427.72" />
      <point x="585.24" y="427.72" />
    </fitbox>
  </object>
  <object>
    <name>pedestrian</name>
    <subname>pedestrian</subname>
    <object_id>1</object_id>
    <bndbox left="627.76" top="385.52" right="642.77" bottom="430.37" />
    <fitbox>
      <point x="627.76" y="385.52" />
      <point x="642.77" y="385.52" />
      <point x="642.77" y="430.37" />
      <point x="627.76" y="430.37" />
    </fitbox>
  </object>
  <object>
    <name>pedestrian</name>
    <subname>pedestrian</subname>
    <object_id>1</object_id>
    <bndbox left="1008.67" top="330.30" right="1066.02" bottom="503.61" />
    <fitbox>
      <point x="1008.67" y="330.30" />
      <point x="1066.02" y="330.30" />
      <point x="1066.02" y="503.61" />
      <point x="1008.67" y="503.61" />
    </fitbox>
  </object>
  <object>
    <name>pedestrian</name>
    <subname>pedestrian</subname>
    <object_id>1</object_id>
    <bndbox left="1111.52" top="329.53" right="1172.72" bottom="536.69" />
    <fitbox>
      <point x="1111.52" y="329.53" />
      <point x="1172.72" y="329.53" />
      <point x="1172.72" y="536.69" />
      <point x="1111.52" y="536.69" />
    </fitbox>
  </object>
  <object>
    <name>pedestrian</name>
    <subname>pedestrian</subname>
    <object_id>1</object_id>
    <bndbox left="29.83" top="404.46" right="58.30" bottom="530.49" />
    <fitbox>
      <point x="29.83" y="404.46" />
      <point x="58.30" y="404.46" />
      <point x="58.30" y="530.49" />
      <point x="29.83" y="530.49" />
    </fitbox>
  </object>
  <object>
    <name>pedestrian</name>
    <subname>pedestrian</subname>
    <object_id>1</object_id>
    <bndbox left="52.62" top="429.05" right="73.65" bottom="500.36" />
    <fitbox>
      <point x="52.62" y="429.05" />
      <point x="73.65" y="429.05" />
      <point x="73.65" y="500.36" />
      <point x="52.62" y="500.36" />
    </fitbox>
  </object>
  <object>
    <name>pedestrian</name>
    <subname>pedestrian</subname>
    <object_id>1</object_id>
    <bndbox left="1085.64" top="378.31" right="1121.94" bottom="491.36" />
    <fitbox>
      <point x="1085.64" y="378.31" />
      <point x="1121.94" y="378.31" />
      <point x="1121.94" y="491.36" />
      <point x="1085.64" y="491.36" />
    </fitbox>
  </object>
  <object>
    <name>pedestrian</name>
    <subname>pedestrian</subname>
    <object_id>1</object_id>
    <bndbox left="223.40" top="411.88" right="242.25" bottom="468.08" />
    <fitbox>
      <point x="223.40" y="411.88" />
      <point x="242.25" y="411.88" />
      <point x="242.25" y="468.08" />
      <point x="223.40" y="468.08" />
    </fitbox>
  </object>
  <object>
    <name>car</name>
    <subname>sedan</subname>
    <object_id>4</object_id>
    <bndbox left="1214.05" top="424.00" right="1280.00" bottom="533.75" />
    <fitbox>
      <point x="1214.05" y="424.00" />
      <point x="1280.00" y="424.00" />
      <point x="1280.00" y="533.75" />
      <point x="1214.05" y="533.75" />
    </fitbox>
  </object>
  <object>
    <name>pedestrian</name>
    <subname>pedestrian</subname>
    <object_id>1</object_id>
    <bndbox left="96.99" top="430.92" right="115.85" bottom="483.38" />
    <fitbox>
      <point x="96.99" y="430.92" />
      <point x="115.85" y="430.92" />
      <point x="115.85" y="483.38" />
      <point x="96.99" y="483.38" />
    </fitbox>
  </object>
  <object>
    <name>pedestrian</name>
    <subname>pedestrian</subname>
    <object_id>1</object_id>
    <bndbox left="71.52" top="433.36" right="89.41" bottom="494.80" />
    <fitbox>
      <point x="71.52" y="433.36" />
      <point x="89.41" y="433.36" />
      <point x="89.41" y="494.80" />
      <point x="71.52" y="494.80" />
    </fitbox>
  </object>
  <object>
    <name>pedestrian</name>
    <subname>pedestrian</subname>
    <object_id>10</object_id>
    <bndbox left="1108.90" top="369.95" right="1144.78" bottom="504.21" />
    <fitbox>
      <point x="1108.90" y="369.95" />
      <point x="1144.78" y="369.95" />
      <point x="1144.78" y="504.21" />
      <point x="1108.90" y="504.21" />
    </fitbox>
  </object>
  <object>
    <name>ignored</name>
    <subname>ignored_vehicle</subname>
    <object_id>11</object_id>
    <bndbox left="76.39" top="435.85" right="110.53" bottom="478.72" />
    <fitbox>
      <point x="76.39" y="435.85" />
      <point x="110.53" y="435.85" />
      <point x="110.53" y="478.72" />
      <point x="76.39" y="478.72" />
    </fitbox>
  </object>
  <object>
    <name>ignored</name>
    <subname>ignored_pedestrian</subname>
    <object_id>12</object_id>
    <bndbox left="1049.86" top="390.99" right="1075.48" bottom="475.74" />
    <fitbox>
      <point x="1049.86" y="390.99" />
      <point x="1075.48" y="390.99" />
      <point x="1075.48" y="475.74" />
      <point x="1049.86" y="475.74" />
    </fitbox>
  </object>
</annotation>